adaptive_tests_py/__init__.py
adaptive_tests_py/__main__.py
adaptive_tests_py/cli.py
adaptive_tests_py/config.py
adaptive_tests_py/discovery.py
adaptive_tests_py/pytest_support.py
adaptive_tests_py/scoring.py
adaptive_tests_py-0.2.5.dist-info/LICENSE
adaptive_tests_py-0.2.5.dist-info/METADATA
adaptive_tests_py-0.2.5.dist-info/WHEEL
adaptive_tests_py-0.2.5.dist-info/entry_points.txt
adaptive_tests_py-0.2.5.dist-info/top_level.txt
adaptive_tests_py-0.2.5.dist-info/RECORD
