Metadata-Version: 2.1
Name: adaptive-tests-py
Version: 0.2.5
Summary: Adaptive test discovery for Python projects
Author-email: Jason Kempf <jasonkempf@gmail.com>
License: MIT
Project-URL: Homepage, https://github.com/anon57396/adaptive-tests
Project-URL: Repository, https://github.com/anon57396/adaptive-tests
Project-URL: Issues, https://github.com/anon57396/adaptive-tests/issues
Classifier: Development Status :: 3 - Alpha
Classifier: Programming Language :: Python :: 3
Classifier: Topic :: Software Development :: Testing
Requires-Python: >=3.8
License-File: LICENSE
Provides-Extra: test
Requires-Dist: pytest >=7.4 ; extra == 'test'
Requires-Dist: pytest-cov >=4.1 ; extra == 'test'
